{
    "swagger": "2.0",
    "info": {
        "version": "2021-04-15-preview1",
        "title": "Azure Communication Server Calling APIs"
    },
    "schemes": [
        "https"
    ],
    "consumes": [
        "application/json"
    ],
    "produces": [
        "application/json"
    ],
    "paths": {
        "/calls": {
            "post": {
                "tags": [
                    "Call"
                ],
                "summary": "Create a new call.",
                "description": "Create a new call.",
                "operationId": "Call_CreateCall",
                "consumes": [
                    "application/json"
                ],
                "produces": [
                    "application/json"
                ],
                "parameters": [
                    {
                        "name": "callRequest",
                        "in": "body",
                        "description": "Create call request.",
                        "required": true,
                        "schema": {
                            "$ref": "#/definitions/CreateCallRequest"
                        }
                    },
                    {
                        "$ref": "#/parameters/ApiVersionParameter"
                    }
                ],
                "responses": {
                    "201": {
                        "description": "Returns the create call response.",
                        "schema": {
                            "$ref": "#/definitions/CreateCallResponse"
                        }
                    },
                    "401": {
                        "description": "Unauthorized",
                        "schema": {
                            "$ref": "#/definitions/CommunicationError"
                        },
                        "x-ms-error-response": true
                    },
                    "400": {
                        "description": "Bad request",
                        "schema": {
                            "$ref": "#/definitions/CommunicationError"
                        },
                        "x-ms-error-response": true
                    },
                    "500": {
                        "description": "Internal server error.",
                        "schema": {
                            "$ref": "#/definitions/CommunicationError"
                        },
                        "x-ms-error-response": true
                    }
                }
            }
        },
        "/calls/{callId}/Hangup": {
            "post": {
                "tags": [
                    "Call"
                ],
                "summary": "Hangup a call.",
                "description": "Hangup a call.",
                "operationId": "Call_HangupCall",
                "consumes": [
                    "application/json"
                ],
                "produces": [
                    "application/json"
                ],
                "parameters": [
                    {
                        "name": "callId",
                        "in": "path",
                        "description": "Call id.",
                        "required": true,
                        "type": "string"
                    },
                    {
                        "$ref": "#/parameters/ApiVersionParameter"
                    }
                ],
                "responses": {
                    "202": {
                        "description": "Returns the hangup call response."
                    },
                    "401": {
                        "description": "Unauthorized",
                        "schema": {
                            "$ref": "#/definitions/CommunicationError"
                        },
                        "x-ms-error-response": true
                    },
                    "400": {
                        "description": "Bad request",
                        "schema": {
                            "$ref": "#/definitions/CommunicationError"
                        },
                        "x-ms-error-response": true
                    },
                    "500": {
                        "description": "Internal server error.",
                        "schema": {
                            "$ref": "#/definitions/CommunicationError"
                        },
                        "x-ms-error-response": true
                    }
                }
            }
        },
        "/calls/{callId}": {
            "delete": {
                "tags": [
                    "Call"
                ],
                "summary": "Delete a call.",
                "description": "Delete a call.",
                "operationId": "Call_DeleteCall",
                "consumes": [
                    "application/json"
                ],
                "produces": [
                    "application/json"
                ],
                "parameters": [
                    {
                        "name": "callId",
                        "in": "path",
                        "description": "Call id.",
                        "required": true,
                        "type": "string"
                    },
                    {
                        "$ref": "#/parameters/ApiVersionParameter"
                    }
                ],
                "responses": {
                    "202": {
                        "description": "Returns the delete call response."
                    },
                    "401": {
                        "description": "Unauthorized",
                        "schema": {
                            "$ref": "#/definitions/CommunicationError"
                        },
                        "x-ms-error-response": true
                    },
                    "400": {
                        "description": "Bad request",
                        "schema": {
                            "$ref": "#/definitions/CommunicationError"
                        },
                        "x-ms-error-response": true
                    },
                    "500": {
                        "description": "Internal server error.",
                        "schema": {
                            "$ref": "#/definitions/CommunicationError"
                        },
                        "x-ms-error-response": true
                    }
                }
            }
        },
        "/calls/{callId}/PlayAudio": {
            "post": {
                "tags": [
                    "Call"
                ],
                "summary": "Play audio in a call.",
                "description": "Play audio in a call.",
                "operationId": "Call_PlayAudio",
                "consumes": [
                    "application/json"
                ],
                "produces": [
                    "application/json"
                ],
                "parameters": [
                    {
                        "name": "callId",
                        "in": "path",
                        "description": "The call id.",
                        "required": true,
                        "type": "string"
                    },
                    {
                        "name": "request",
                        "in": "body",
                        "description": "Play audio request.",
                        "required": true,
                        "schema": {
                            "$ref": "#/definitions/PlayAudioRequest"
                        }
                    },
                    {
                        "$ref": "#/parameters/ApiVersionParameter"
                    }
                ],
                "responses": {
                    "202": {
                        "description": "Returns the play audio response.",
                        "schema": {
                            "$ref": "#/definitions/PlayAudioResponse"
                        }
                    },
                    "401": {
                        "description": "Unauthorized",
                        "schema": {
                            "$ref": "#/definitions/CommunicationError"
                        },
                        "x-ms-error-response": true
                    },
                    "400": {
                        "description": "Bad request",
                        "schema": {
                            "$ref": "#/definitions/CommunicationError"
                        },
                        "x-ms-error-response": true
                    },
                    "500": {
                        "description": "Internal server error.",
                        "schema": {
                            "$ref": "#/definitions/CommunicationError"
                        },
                        "x-ms-error-response": true
                    }
                }
            }
        },
        "/calls/{callId}/CancelMediaProcessing": {
            "post": {
                "tags": [
                    "Call"
                ],
                "summary": "Cancel Media Processing.",
                "description": "Cancel Media Processing.",
                "operationId": "Call_CancelMediaProcessing",
                "consumes": [
                    "application/json"
                ],
                "produces": [
                    "application/json"
                ],
                "parameters": [
                    {
                        "name": "callId",
                        "in": "path",
                        "description": "The call id",
                        "required": true,
                        "type": "string"
                    },
                    {
                        "name": "request",
                        "in": "body",
                        "description": "The cancel media processing request.",
                        "required": true,
                        "schema": {
                            "$ref": "#/definitions/CancelMediaProcessingRequest"
                        }
                    },
                    {
                        "$ref": "#/parameters/ApiVersionParameter"
                    }
                ],
                "responses": {
                    "200": {
                        "description": "Returns the cancel media processing response.",
                        "schema": {
                            "$ref": "#/definitions/CancelMediaProcessingResponse"
                        }
                    },
                    "401": {
                        "description": "Unauthorized",
                        "schema": {
                            "$ref": "#/definitions/CommunicationError"
                        },
                        "x-ms-error-response": true
                    },
                    "400": {
                        "description": "Bad request",
                        "schema": {
                            "$ref": "#/definitions/CommunicationError"
                        },
                        "x-ms-error-response": true
                    },
                    "500": {
                        "description": "Internal server error.",
                        "schema": {
                            "$ref": "#/definitions/CommunicationError"
                        },
                        "x-ms-error-response": true
                    }
                }
            }
        },
        "/calls/{callId}/participants": {
            "post": {
                "tags": [
                    "Participant"
                ],
                "summary": "Invite participants to the call.",
                "description": "Invite participants to the call.",
                "operationId": "Call_InviteParticipants",
                "consumes": [
                    "application/json"
                ],
                "produces": [
                    "application/json"
                ],
                "parameters": [
                    {
                        "name": "callId",
                        "in": "path",
                        "description": "Call id.",
                        "required": true,
                        "type": "string"
                    },
                    {
                        "name": "inviteParticipantsRequest",
                        "in": "body",
                        "description": "Invite participant request.",
                        "required": true,
                        "schema": {
                            "$ref": "#/definitions/InviteParticipantsRequest"
                        }
                    },
                    {
                        "$ref": "#/parameters/ApiVersionParameter"
                    }
                ],
                "responses": {
                    "202": {
                        "description": "Returns the invite participants response."
                    },
                    "401": {
                        "description": "Unauthorized",
                        "schema": {
                            "$ref": "#/definitions/CommunicationError"
                        },
                        "x-ms-error-response": true
                    },
                    "400": {
                        "description": "Bad request",
                        "schema": {
                            "$ref": "#/definitions/CommunicationError"
                        },
                        "x-ms-error-response": true
                    },
                    "500": {
                        "description": "Internal server error.",
                        "schema": {
                            "$ref": "#/definitions/CommunicationError"
                        },
                        "x-ms-error-response": true
                    }
                }
            }
        },
        "/calls/{callId}/participants/{participantId}": {
            "delete": {
                "tags": [
                    "Participant"
                ],
                "summary": "Remove participant from the call.",
                "description": "Remove participant from the call.",
                "operationId": "Call_RemoveParticipant",
                "consumes": [
                    "application/json"
                ],
                "produces": [
                    "application/json"
                ],
                "parameters": [
                    {
                        "name": "callId",
                        "in": "path",
                        "description": "Call id.",
                        "required": true,
                        "type": "string"
                    },
                    {
                        "name": "participantId",
                        "in": "path",
                        "description": "Participant id.",
                        "required": true,
                        "type": "string"
                    },
                    {
                        "$ref": "#/parameters/ApiVersionParameter"
                    }
                ],
                "responses": {
                    "202": {
                        "description": "Returns the remove participant response."
                    },
                    "401": {
                        "description": "Unauthorized",
                        "schema": {
                            "$ref": "#/definitions/CommunicationError"
                        },
                        "x-ms-error-response": true
                    },
                    "400": {
                        "description": "Bad request",
                        "schema": {
                            "$ref": "#/definitions/CommunicationError"
                        },
                        "x-ms-error-response": true
                    },
                    "500": {
                        "description": "Internal server error.",
                        "schema": {
                            "$ref": "#/definitions/CommunicationError"
                        },
                        "x-ms-error-response": true
                    }
                }
            }
        },
        "/conversations/{conversationId}/Recordings": {
            "post": {
                "tags": [
                    "Recording"
                ],
                "summary": "Start call recording request",
                "operationId": "Recording_StartRecording",
                "consumes": [
                    "application/json"
                ],
                "produces": [
                    "application/json"
                ],
                "parameters": [
                    {
                        "name": "conversationId",
                        "in": "path",
                        "description": "Encoded conversation url.",
                        "required": true,
                        "type": "string"
                    },
                    {
                        "name": "request",
                        "in": "body",
                        "description": "Request body of start call recording request.",
                        "required": true,
                        "schema": {
                            "$ref": "#/definitions/StartCallRecordingRequest"
                        }
                    },
                    {
                        "$ref": "#/parameters/ApiVersionParameter"
                    }
                ],
                "responses": {
                    "200": {
                        "description": "Returns the start call recording response.",
                        "schema": {
                            "$ref": "#/definitions/StartCallRecordingResponse"
                        }
                    },
                    "400": {
                        "description": "Bad request",
                        "schema": {
                            "$ref": "#/definitions/CommunicationError"
                        },
                        "x-ms-error-response": true
                    },
                    "404": {
                        "description": "Not found.",
                        "schema": {
                            "$ref": "#/definitions/CommunicationError"
                        },
                        "x-ms-error-response": true
                    },
                    "500": {
                        "description": "Internal server error.",
                        "schema": {
                            "$ref": "#/definitions/CommunicationError"
                        },
                        "x-ms-error-response": true
                    }
                }
            }
        },
        "/conversations/{conversationId}/recordings/{recordingId}": {
            "get": {
                "tags": [
                    "Recording"
                ],
                "summary": "Get call recording state.",
                "operationId": "Recording_RecordingState",
                "consumes": [
                    "application/json"
                ],
                "produces": [
                    "application/json"
                ],
                "parameters": [
                    {
                        "name": "conversationId",
                        "in": "path",
                        "description": "Encoded conversation url.",
                        "required": true,
                        "type": "string"
                    },
                    {
                        "name": "recordingId",
                        "in": "path",
                        "description": "Recording id.",
                        "required": true,
                        "type": "string"
                    },
                    {
                        "name": "request.operationContext",
                        "in": "query",
                        "description": "The context of the operation.",
                        "required": false,
                        "type": "string"
                    },
                    {
                        "$ref": "#/parameters/ApiVersionParameter"
                    }
                ],
                "responses": {
                    "200": {
                        "description": "Returns the recording state.",
                        "schema": {
                            "$ref": "#/definitions/GetCallRecordingStateResponse"
                        }
                    },
                    "400": {
                        "description": "Bad request",
                        "schema": {
                            "$ref": "#/definitions/CommunicationError"
                        },
                        "x-ms-error-response": true
                    },
                    "404": {
                        "description": "Not found.",
                        "schema": {
                            "$ref": "#/definitions/CommunicationError"
                        },
                        "x-ms-error-response": true
                    },
                    "500": {
                        "description": "Internal server error.",
                        "schema": {
                            "$ref": "#/definitions/CommunicationError"
                        },
                        "x-ms-error-response": true
                    }
                }
            },
            "delete": {
                "tags": [
                    "Recording"
                ],
                "summary": "Stop recording a call.",
                "operationId": "Recording_StopRecording",
                "consumes": [
                    "application/json"
                ],
                "produces": [
                    "application/json"
                ],
                "parameters": [
                    {
                        "name": "conversationId",
                        "in": "path",
                        "description": "Encoded conversation url.",
                        "required": true,
                        "type": "string"
                    },
                    {
                        "name": "recordingId",
                        "in": "path",
                        "description": "Recording id.",
                        "required": true,
                        "type": "string"
                    },
                    {
                        "name": "request",
                        "in": "body",
                        "description": "Request body of stop call recording request.",
                        "required": true,
                        "schema": {
                            "$ref": "#/definitions/StopCallRecordingRequest"
                        }
                    },
                    {
                        "$ref": "#/parameters/ApiVersionParameter"
                    }
                ],
                "responses": {
                    "200": {
                        "description": "Returns the stop call recording response."
                    },
                    "400": {
                        "description": "Bad request",
                        "schema": {
                            "$ref": "#/definitions/CommunicationError"
                        },
                        "x-ms-error-response": true
                    },
                    "500": {
                        "description": "Internal server error.",
                        "schema": {
                            "$ref": "#/definitions/CommunicationError"
                        },
                        "x-ms-error-response": true
                    }
                }
            }
        },
        "/conversations/{conversationId}/recordings/{recordingId}/Pause": {
            "post": {
                "tags": [
                    "Recording"
                ],
                "summary": "Pause recording a call.",
                "operationId": "Recording_PauseRecording",
                "consumes": [
                    "application/json"
                ],
                "produces": [
                    "application/json"
                ],
                "parameters": [
                    {
                        "name": "conversationId",
                        "in": "path",
                        "description": "Encoded conversation url.",
                        "required": true,
                        "type": "string"
                    },
                    {
                        "name": "recordingId",
                        "in": "path",
                        "description": "Recording id.",
                        "required": true,
                        "type": "string"
                    },
                    {
                        "name": "request",
                        "in": "body",
                        "description": "Request body of pause call recording request.",
                        "required": true,
                        "schema": {
                            "$ref": "#/definitions/PauseCallRecordingRequest"
                        }
                    },
                    {
                        "$ref": "#/parameters/ApiVersionParameter"
                    }
                ],
                "responses": {
                    "200": {
                        "description": "Returns the pause call recording response."
                    },
                    "400": {
                        "description": "Bad request",
                        "schema": {
                            "$ref": "#/definitions/CommunicationError"
                        },
                        "x-ms-error-response": true
                    },
                    "500": {
                        "description": "Internal server error.",
                        "schema": {
                            "$ref": "#/definitions/CommunicationError"
                        },
                        "x-ms-error-response": true
                    }
                }
            }
        },
        "/conversations/{conversationId}/recordings/{recordingId}/Resume": {
            "post": {
                "tags": [
                    "Recording"
                ],
                "summary": "Resume recording a call.",
                "operationId": "Recording_ResumeRecording",
                "consumes": [
                    "application/json"
                ],
                "produces": [
                    "application/json"
                ],
                "parameters": [
                    {
                        "name": "conversationId",
                        "in": "path",
                        "description": "Encoded conversation url.",
                        "required": true,
                        "type": "string"
                    },
                    {
                        "name": "recordingId",
                        "in": "path",
                        "description": "Recording id.",
                        "required": true,
                        "type": "string"
                    },
                    {
                        "name": "request",
                        "in": "body",
                        "description": "Request body of resume call recording request.",
                        "required": true,
                        "schema": {
                            "$ref": "#/definitions/ResumeCallRecordingRequest"
                        }
                    },
                    {
                        "$ref": "#/parameters/ApiVersionParameter"
                    }
                ],
                "responses": {
                    "200": {
                        "description": "Returns the resume call recording response."
                    },
                    "400": {
                        "description": "Bad request",
                        "schema": {
                            "$ref": "#/definitions/CommunicationError"
                        },
                        "x-ms-error-response": true
                    },
                    "500": {
                        "description": "Internal server error.",
                        "schema": {
                            "$ref": "#/definitions/CommunicationError"
                        },
                        "x-ms-error-response": true
                    }
                }
            }
        }
    },
    "definitions": {
        "CallModality": {
            "enum": [
                "audio",
                "video"
            ],
            "type": "string",
            "x-ms-enum": {
                "name": "CallModality",
                "modelAsString": true
            }
        },
        "EventSubscriptionType": {
            "enum": [
                "participantsUpdated",
                "dtmfReceived"
            ],
            "type": "string",
            "x-ms-enum": {
                "name": "EventSubscriptionType",
                "modelAsString": true
            }
        },
        "CreateCallRequest": {
            "description": "The request payload for creating a call.",
            "required": [
                "source",
                "targets",
                "callbackUri",
                "requestedModalities",
                "requestedCallEvents"
            ],
            "type": "object",
            "properties": {
                "source": {
                    "$ref": "#/definitions/CommunicationIdentifier",
                    "description": "The source of the call."
                },
                "sourceAlternateIdentity": {
                    "$ref": "#/definitions/PhoneNumberIdentifier",
                    "description": "The alternate identity of the source of the call if dialing out to a pstn number"
                },
                "targets": {
                    "description": "The targets of the call.",
                    "type": "array",
                    "items": {
                        "$ref": "#/definitions/CommunicationIdentifier"
                    }
                },
                "subject": {
                    "description": "The subject.",
                    "type": "string"
                },
                "callbackUri": {
                    "description": "The callback URI.",
                    "type": "string"
                },
                "requestedModalities": {
                    "description": "The requested modalities.",
                    "type": "array",
                    "items": {
                        "$ref": "#/definitions/CallModality"
                    }
                },
                "requestedCallEvents": {
                    "description": "The requested call events to subscribe to.",
                    "type": "array",
                    "items": {
                        "$ref": "#/definitions/EventSubscriptionType"
                    }
                }
            }
        },
        "CommunicationIdentifier": {
            "$ref": "https://github.com/Azure/azure-rest-api-specs/tree/master/specification/communication/data-plane/Microsoft.CommunicationServicesCommon/stable/2021-03-07/common.json#/definitions/CommunicationIdentifierModel"
        },
        "PhoneNumberIdentifier": {
            "$ref": "https://github.com/Azure/azure-rest-api-specs/tree/master/specification/communication/data-plane/Microsoft.CommunicationServicesCommon/stable/2021-03-07/common.json#/definitions/PhoneNumberIdentifierModel"
        },
        "CommunicationUserIdentifier": {
            "$ref": "https://github.com/Azure/azure-rest-api-specs/tree/master/specification/communication/data-plane/Microsoft.CommunicationServicesCommon/stable/2021-03-07/common.json#/definitions/CommunicationUserIdentifierModel"
        },
        "CommunicationCloudEnvironment": {
            "$ref": "https://github.com/Azure/azure-rest-api-specs/tree/master/specification/communication/data-plane/Microsoft.CommunicationServicesCommon/stable/2021-03-07/common.json#/definitions/CommunicationCloudEnvironmentModel"
        },
        "MicrosoftTeamsUserIdentifier": {
            "$ref": "https://github.com/Azure/azure-rest-api-specs/tree/master/specification/communication/data-plane/Microsoft.CommunicationServicesCommon/stable/2021-03-07/common.json#/definitions/MicrosoftTeamsUserIdentifierModel"
        },
        "CreateCallResponse": {
            "description": "The response payload of the create call operation.",
            "type": "object",
            "properties": {
                "callLegId": {
                    "description": "Call leg id of the call.",
                    "type": "string"
                }
            }
        },
        "CommunicationError": {
            "$ref": "https://github.com/Azure/azure-rest-api-specs/tree/master/specification/communication/data-plane/Microsoft.CommunicationServicesCommon/stable/2021-03-07/common.json#/definitions/CommunicationError"
        },
        "PlayAudioRequest": {
            "description": "The request payload for playing audio.",
            "type": "object",
            "properties": {
                "audioFileUri": {
                    "description": "The media resource uri of the play audio request. \r\nCurrently only Wave file (.wav) format audio prompts are supported.\r\nMore specifically, the audio content in the wave file must be mono (single-channel),\r\n16-bit samples with a 16,000 (16KHz) sampling rate.",
                    "type": "string"
                },
                "loop": {
                    "description": "The flag indicating whether audio file needs to be played in loop or not.",
                    "type": "boolean"
                },
                "operationContext": {
                    "description": "The value to identify context of the operation.",
                    "type": "string"
                },
                "resourceId": {
                    "description": "The media resource id of the play audio request. A ResourceId value\r\nindicates the media resource should be cached within the runtime service\r\nwhich handles playing audios.",
                    "type": "string"
                }
            }
        },
        "OperationStatus": {
            "description": "Gets or sets the status of the operation",
            "enum": [
                "notStarted",
                "running",
                "completed",
                "failed"
            ],
            "type": "string",
            "x-ms-enum": {
                "name": "OperationStatus",
                "modelAsString": true
            }
        },
        "PlayAudioResponse": {
            "description": "The response payload for play audio operation.",
            "type": "object",
            "properties": {
                "id": {
                    "description": "Gets or sets the identifier.",
                    "type": "string"
                },
                "status": {
                    "$ref": "#/definitions/OperationStatus"
                },
                "operationContext": {
                    "description": "Gets or sets the operation context",
                    "type": "string"
                },
                "resultInfo": {
                    "$ref": "#/definitions/ResultInfo",
                    "description": "Gets or sets the result info"
                }
            }
        },
        "ResultInfo": {
            "description": "Result info class to be used to report result status for actions/operations.",
            "type": "object",
            "properties": {
                "code": {
                    "format": "int32",
                    "description": "Gets or sets the result code\r\nFor synchronous failures, this maps one-to-one with HTTP responses. For asynchronous failures or messages, it is contextual.",
                    "type": "integer"
                },
                "subcode": {
                    "format": "int32",
                    "description": "Gets or sets the result subcode.\r\nThe subcode further classifies a failure. For example.",
                    "type": "integer"
                },
                "message": {
                    "description": "Gets or sets the message\r\nThe message is a detail explanation of subcode.",
                    "type": "string"
                }
            }
        },
        "CancelMediaProcessingRequest": {
            "description": "The request payload for cancel media processing",
            "type": "object",
            "properties": {
                "operationContext": {
                    "description": "The context for this operation.",
                    "type": "string"
                }
            }
        },
        "CancelMediaProcessingResponse": {
            "description": "The response payload of the cancel media processing operation.",
            "type": "object",
            "properties": {
                "id": {
                    "description": "Gets or sets the identifier.",
                    "type": "string"
                },
                "status": {
                    "$ref": "#/definitions/OperationStatus"
                },
                "operationContext": {
                    "description": "Gets or sets the operation context",
                    "type": "string"
                },
                "resultInfo": {
                    "$ref": "#/definitions/ResultInfo",
                    "description": "Gets or sets the result info"
                }
            }
        },
        "InviteParticipantsRequest": {
            "description": "The invite participants request.",
            "required": [
                "participants"
            ],
            "type": "object",
            "properties": {
                "alternateCallerId": {
                    "$ref": "#/definitions/PhoneNumberIdentifier",
                    "description": "The alternate identity of source participant."
                },
                "participants": {
                    "description": "The list of participants to be added to the call.",
                    "type": "array",
                    "items": {
                        "$ref": "#/definitions/CommunicationIdentifier"
                    }
                },
                "operationContext": {
                    "description": "The operation context.",
                    "type": "string"
                }
            }
        },
        "StartCallRecordingRequest": {
            "description": "The request payload start call recording operation.",
            "type": "object",
            "properties": {
                "operationContext": {
                    "description": "The context for this operation.",
                    "type": "string"
                },
                "recordingStateCallbackUri": {
                    "description": "The uri to send notifications to.",
                    "type": "string"
                }
            }
        },
        "StartCallRecordingResponse": {
            "description": "The response payload of start call recording operation.",
            "type": "object",
            "properties": {
                "recordingId": {
                    "description": "The recording id of the started recording",
                    "type": "string"
                }
            }
        },
        "GetCallRecordingStateRequest": {
            "description": "The request payload of get call recording state operation.",
            "type": "object",
            "properties": {
                "operationContext": {
                    "description": "The context of the operation.",
                    "type": "string"
                }
            }
        },
        "CallRecordingState": {
            "description": "The recording state of the recording",
            "enum": [
                "active",
                "inactive"
            ],
            "type": "string",
            "x-ms-enum": {
                "name": "CallRecordingState",
                "modelAsString": true
            }
        },
        "GetCallRecordingStateResponse": {
            "description": "The response payload of get call recording state operation.",
            "type": "object",
            "properties": {
                "recordingState": {
                    "$ref": "#/definitions/CallRecordingState"
                }
            }
        },
        "StopCallRecordingRequest": {
            "description": "The request payload of stop call recording operation.",
            "type": "object",
            "properties": {
                "operationContext": {
                    "description": "The context of the operation.",
                    "type": "string"
                }
            }
        },
        "PauseCallRecordingRequest": {
            "description": "The request payload pause call recording operation.",
            "type": "object",
            "properties": {
                "operationContext": {
                    "description": "The context of the operation.",
                    "type": "string"
                }
            }
        },
        "ResumeCallRecordingRequest": {
            "description": "The request payload of resume call recording operation.",
            "type": "object",
            "properties": {
                "operationContext": {
                    "description": "The context of the operation.",
                    "type": "string"
                }
            }
        }
    },
    "parameters": {
        "ApiVersionParameter": {
            "name": "api-version",
            "in": "query",
            "description": "Version of API to invoke.",
            "required": true,
            "type": "string",
            "x-ms-parameter-location": "method"
        },
        "Endpoint": {
            "name": "endpoint",
            "in": "path",
            "description": "The endpoint of the Azure Communication resource.",
            "required": true,
            "type": "string",
            "x-ms-skip-url-encoding": true,
            "x-ms-parameter-location": "client"
        }
    },
    "x-ms-parameterized-host": {
        "hostTemplate": "{endpoint}",
        "useSchemePrefix": false,
        "parameters": [
            {
                "$ref": "#/parameters/Endpoint"
            }
        ]
    }
}
